<MetaData>
    <WCODataModelVersionCode>3.6</WCODataModelVersionCode>
    <WCOTypeName>RES</WCOTypeName>
    <ResponsibleCountryCode/>
    <ResponsibleAgencyName/>
    <AgencyAssignedCustomizationCode/>
    <AgencyAssignedCustomizationVersionCode/>
    <Response>
        <FunctionCode>02</FunctionCode>
        <FunctionalReferenceID>ff6058dfba464b4d9395348cd76bb86a</FunctionalReferenceID>
        <IssueDateTime>
            <DateTimeString formatCode="304">20221209150430Z</DateTimeString>
        </IssueDateTime>
        <Declaration>
            <FunctionalReferenceID>TC01_InvalidateM1</FunctionalReferenceID>
            <ID>22GBDLDO49YEKLWAA4</ID>
        </Declaration>
    </Response>
</MetaData>