<MetaData>
    <WCODataModelVersionCode>3.6</WCODataModelVersionCode>
    <WCOTypeName>RES</WCOTypeName>
    <ResponsibleCountryCode/>
    <ResponsibleAgencyName/>
    <AgencyAssignedCustomizationCode/>
    <AgencyAssignedCustomizationVersionCode/>
    <Response>
        <FunctionCode>01</FunctionCode>
        <FunctionalReferenceID>d357fc1ff10347688070e0ecbb27074a</FunctionalReferenceID>
        <IssueDateTime>
            <DateTimeString formatCode="304">20240614164157+01</DateTimeString>
        </IssueDateTime>
        <Declaration>
            <AcceptanceDateTime>
                <DateTimeString formatCode="304">20240614164156+01</DateTimeString>
            </AcceptanceDateTime>
            <FunctionalReferenceID>7867523JVFNS</FunctionalReferenceID>
            <ID>24GB6KPAP6N7X13AR3</ID>
            <VersionID>2</VersionID>
        </Declaration>
    </Response>
</MetaData>