<MetaData>
	<WCODataModelVersionCode>3.6</WCODataModelVersionCode>
	<WCOTypeName>RES</WCOTypeName>
	<ResponsibleCountryCode/>
	<ResponsibleAgencyName/>
	<AgencyAssignedCustomizationCode/>
	<AgencyAssignedCustomizationVersionCode/>
	<Response>
		<FunctionCode>09</FunctionCode>
		<FunctionalReferenceID>ec6f60d2287d403c973754d26a592ebe</FunctionalReferenceID>
		<IssueDateTime>
			<DateTimeString formatCode="304">20240912111149Z</DateTimeString>
		</IssueDateTime>
		<AdditionalInformation>
			<StatementCode>A2</StatementCode>
			<StatementTypeCode>AFB</StatementTypeCode>
		</AdditionalInformation>
		<Declaration>
			<FunctionalReferenceID>7849431WQBXX</FunctionalReferenceID>
			<ID>24GBA51A5S7U0KGAR1</ID>
			<VersionID>1</VersionID>
		</Declaration>
	</Response>
</MetaData>