<MetaData>
	<WCODataModelVersionCode>3.6</WCODataModelVersionCode>
	<WCOTypeName>RES</WCOTypeName>
	<ResponsibleCountryCode/>
	<ResponsibleAgencyName/>
	<AgencyAssignedCustomizationCode/>
	<AgencyAssignedCustomizationVersionCode/>
	<Response>
		<FunctionCode>01</FunctionCode>
		<FunctionalReferenceID>381129feb7794056b1abb7e1336ac7ba</FunctionalReferenceID>
		<IssueDateTime>
			<DateTimeString formatCode="304">20230609082628+01</DateTimeString>
		</IssueDateTime>
		<Declaration>
			<AcceptanceDateTime>
				<DateTimeString formatCode="304">20230609000000+01</DateTimeString>
			</AcceptanceDateTime>
			<FunctionalReferenceID>784830983BP8J16J8</FunctionalReferenceID>
			<ID>23GB6BMYKQPD989AR5</ID>
			<VersionID>1</VersionID>
		</Declaration>
	</Response>
</MetaData>