<?xml version="1.0" encoding="UTF-8"?>
<MetaData>
	<WCODataModelVersionCode>3.6</WCODataModelVersionCode>
	<WCOTypeName>RES</WCOTypeName>
	<ResponsibleCountryCode/>
	<ResponsibleAgencyName/>
	<AgencyAssignedCustomizationCode/>
	<AgencyAssignedCustomizationVersionCode/>
	<Response>
		<FunctionCode>13</FunctionCode>
		<FunctionalReferenceID>f153454a1dd949599b55d1d268f7376b</FunctionalReferenceID>
		<IssueDateTime>
			<DateTimeString formatCode="304">20260220091345Z</DateTimeString>
		</IssueDateTime>
		<Bank>
			<ReferenceID>BARCGB22</ReferenceID>
			<ID>GB16BARC20051723372545</ID>
		</Bank>
		<Status>
			<NameCode>67</NameCode>
		</Status>
		<Declaration>
			<FunctionalReferenceID>U.7867523V2X5J</FunctionalReferenceID>
			<ID>26GB1ZZSPEO89PVAR0</ID>
			<VersionID>1</VersionID>
			<GoodsShipment>
				<GovernmentAgencyGoodsItem>
					<SequenceNumeric>1</SequenceNumeric>
					<Commodity>
						<DutyTaxFee>
							<DeductAmount currencyID="GBP">0.00</DeductAmount>
							<DutyRegimeCode>100</DutyRegimeCode>
							<TypeCode>A00</TypeCode>
							<Payment>
								<TaxAssessedAmount currencyID="GBP">30.88</TaxAssessedAmount>
								<PaymentAmount currencyID="GBP">30.88</PaymentAmount>
							</Payment>
						</DutyTaxFee>
						<DutyTaxFee>
							<AdValoremTaxBaseAmount currencyID="GBP">141.88</AdValoremTaxBaseAmount>
							<DeductAmount currencyID="GBP">0.00</DeductAmount>
							<DutyRegimeCode>100</DutyRegimeCode>
							<TaxRateNumeric>20.00</TaxRateNumeric>
							<TypeCode>B00</TypeCode>
							<Payment>
								<TaxAssessedAmount currencyID="GBP">28.37</TaxAssessedAmount>
								<PaymentAmount currencyID="GBP">28.37</PaymentAmount>
							</Payment>
						</DutyTaxFee>
					</Commodity>
				</GovernmentAgencyGoodsItem>
			</GoodsShipment>
		</Declaration>
	</Response>
</MetaData>