<MetaData>
	<WCODataModelVersionCode>3.6</WCODataModelVersionCode>
	<WCOTypeName>RES</WCOTypeName>
	<ResponsibleCountryCode/>
	<ResponsibleAgencyName/>
	<AgencyAssignedCustomizationCode/>
	<AgencyAssignedCustomizationVersionCode/>
	<Response>
		<FunctionCode>09</FunctionCode>
		<FunctionalReferenceID>12d881d05b314ed2b598dadb1fe3624f</FunctionalReferenceID>
		<IssueDateTime>
			<DateTimeString formatCode="304">20240912105744Z</DateTimeString>
		</IssueDateTime>
		<AdditionalInformation>
			<StatementCode>A2</StatementCode>
			<StatementTypeCode>AFB</StatementTypeCode>
		</AdditionalInformation>
		<Declaration>
			<FunctionalReferenceID>7849431TW38W</FunctionalReferenceID>
			<ID>24GBA50RWP2XN0QA03</ID>
			<VersionID>2</VersionID>
		</Declaration>
	</Response>
</MetaData>