<MetaData>
    <WCODataModelVersionCode>3.6</WCODataModelVersionCode>
    <WCOTypeName>RES</WCOTypeName>
    <ResponsibleCountryCode/>
    <ResponsibleAgencyName/>
    <AgencyAssignedCustomizationCode/>
    <AgencyAssignedCustomizationVersionCode/>
    <Response>
        <FunctionCode>09</FunctionCode>
        <FunctionalReferenceID>b23c26e00a3145f18df83d4d46227580</FunctionalReferenceID>
        <IssueDateTime>
            <DateTimeString formatCode="304">20221214101939Z</DateTimeString>
        </IssueDateTime>
        <AdditionalInformation>
            <StatementCode>A2</StatementCode>
            <StatementTypeCode>AFB</StatementTypeCode>
        </AdditionalInformation>
        <Declaration>
            <FunctionalReferenceID>TT_IM26a_v1.5_1412_01</FunctionalReferenceID>
            <ID>22GBDSFU1TEBSLLAR2</ID>
            <VersionID>2</VersionID>
        </Declaration>
    </Response>
</MetaData>