<MetaData>
	<WCODataModelVersionCode>3.6</WCODataModelVersionCode>
	<WCOTypeName>RES</WCOTypeName>
	<ResponsibleCountryCode/>
	<ResponsibleAgencyName/>
	<AgencyAssignedCustomizationCode/>
	<AgencyAssignedCustomizationVersionCode/>
	<Response>
		<FunctionCode>01</FunctionCode>
		<FunctionalReferenceID>83a7649097324e7bacc87e3ebd398350</FunctionalReferenceID>
		<IssueDateTime>
			<DateTimeString formatCode="304">20210915134207Z</DateTimeString>
		</IssueDateTime>
		<Declaration>
			<AcceptanceDateTime>
				<DateTimeString formatCode="304">20210915144205Z</DateTimeString>
			</AcceptanceDateTime>
			<FunctionalReferenceID>B4DATASET_2PAY15092</FunctionalReferenceID>
			<ID>21GBA81GIYFIFGZME6</ID>
			<VersionID>2</VersionID>
		</Declaration>
	</Response>
</MetaData>