<ns2:inventoryLinkingMovementTotalsResponse xmlns="http://gov.uk/customs/inventoryLinking/gatewayHeader/v1" xmlns:ns2="http://gov.uk/customs/inventoryLinking/v1">
	<ns2:messageCode>EMR</ns2:messageCode>
	<ns2:crc>000</ns2:crc>
	<ns2:goodsLocation>GBAULHRLHRANS</ns2:goodsLocation>
	<ns2:masterUCR>GB/TI8P-DT2WQ1EZIAGHEHNEGYCIISCAL</ns2:masterUCR>
	<ns2:declarationCount>2</ns2:declarationCount>
	<ns2:goodsArrivalDateTime>2025-05-02T10:08:23.023Z</ns2:goodsArrivalDateTime>
	<ns2:movementReference>94RHWX8J8DYX1SR90IFZFEH3J</ns2:movementReference>
	<ns2:masterROE>6</ns2:masterROE>
	<ns2:masterSOE>3</ns2:masterSOE>
	<ns2:entry>
		<ns2:ucrBlock>
			<ns2:ucr>5GB978637785572-W6RDJM</ns2:ucr>
			<ns2:ucrType>D</ns2:ucrType>
		</ns2:ucrBlock>
		<ns2:entryStatus>
			<ns2:roe>6</ns2:roe>
			<ns2:soe>3</ns2:soe>
		</ns2:entryStatus>
	</ns2:entry>
	<ns2:entry>
		<ns2:ucrBlock>
			<ns2:ucr>5GB778233511008-V6W4ZS</ns2:ucr>
			<ns2:ucrType>D</ns2:ucrType>
		</ns2:ucrBlock>
		<ns2:entryStatus>
			<ns2:roe>6</ns2:roe>
			<ns2:soe>3</ns2:soe>
		</ns2:entryStatus>
	</ns2:entry>
</ns2:inventoryLinkingMovementTotalsResponse>