
<MetaData>
	<WCODataModelVersionCode>3.6</WCODataModelVersionCode>
	<WCOTypeName>RES</WCOTypeName>
	<ResponsibleCountryCode/>
	<ResponsibleAgencyName/>
	<AgencyAssignedCustomizationCode/>
	<AgencyAssignedCustomizationVersionCode/>
	<Response>
		<FunctionCode>13</FunctionCode>
		<FunctionalReferenceID>1c55b00d32ee4335891790289daa80fc</FunctionalReferenceID>
		<IssueDateTime>
			<DateTimeString formatCode="304">20260528102932Z</DateTimeString>
		</IssueDateTime>
		<Bank>
			<ReferenceID>BARCGB22</ReferenceID>
			<ID>GB16BARC20051723372545</ID>
		</Bank>
		<Status>
			<NameCode>4</NameCode>
		</Status>
		<Declaration>
			<FunctionalReferenceID>U.7927468UNNFD</FunctionalReferenceID>
			<ID>26GB5UO1QDOVBJAAR6</ID>
			<VersionID>1</VersionID>
			<GoodsShipment>
				<GovernmentAgencyGoodsItem>
					<SequenceNumeric>1</SequenceNumeric>
					<Commodity>
						<DutyTaxFee>
							<AdValoremTaxBaseAmount currencyID="GBP">61.10</AdValoremTaxBaseAmount>
							<DeductAmount currencyID="GBP">0.00</DeductAmount>
							<DutyRegimeCode>100</DutyRegimeCode>
							<TaxRateNumeric>20.00</TaxRateNumeric>
							<TypeCode>B05</TypeCode>
							<Payment>
								<TaxAssessedAmount currencyID="GBP">12.22</TaxAssessedAmount>
								<PaymentAmount currencyID="GBP">12.22</PaymentAmount>
							</Payment>
						</DutyTaxFee>
						<DutyTaxFee>
							<AdValoremTaxBaseAmount currencyID="GBP">1300.00</AdValoremTaxBaseAmount>
							<DeductAmount currencyID="GBP">0.00</DeductAmount>
							<DutyRegimeCode>100</DutyRegimeCode>
							<TaxRateNumeric>20.00</TaxRateNumeric>
							<TypeCode>B00</TypeCode>
							<Payment>
								<TaxAssessedAmount currencyID="GBP">260.00</TaxAssessedAmount>
								<PaymentAmount currencyID="GBP">260.00</PaymentAmount>
							</Payment>
						</DutyTaxFee>
						<DutyTaxFee>
							<AdValoremTaxBaseAmount currencyID="GBP">1300.00</AdValoremTaxBaseAmount>
							<DeductAmount currencyID="GBP">0.00</DeductAmount>
							<DutyRegimeCode>100</DutyRegimeCode>
							<TaxRateNumeric>4.70</TaxRateNumeric>
							<TypeCode>A50</TypeCode>
							<Payment>
								<TaxAssessedAmount currencyID="GBP">61.10</TaxAssessedAmount>
								<PaymentAmount currencyID="GBP">61.10</PaymentAmount>
							</Payment>
						</DutyTaxFee>
					</Commodity>
				</GovernmentAgencyGoodsItem>
			</GoodsShipment>
		</Declaration>
	</Response>
</MetaData>