<MetaData>
	<WCODataModelVersionCode>3.6</WCODataModelVersionCode>
	<WCOTypeName>RES</WCOTypeName>
	<ResponsibleCountryCode/>
	<ResponsibleAgencyName/>
	<AgencyAssignedCustomizationCode/>
	<AgencyAssignedCustomizationVersionCode/>
	<Response>
		<FunctionCode>01</FunctionCode>
		<FunctionalReferenceID>ccb38d173caf493282a7bae175cbc091</FunctionalReferenceID>
		<IssueDateTime>
			<DateTimeString formatCode="304">20240916113714Z</DateTimeString>
		</IssueDateTime>
		<Declaration>
			<AcceptanceDateTime>
				<DateTimeString formatCode="304">20240916113712Z</DateTimeString>
			</AcceptanceDateTime>
			<FunctionalReferenceID>7847767CYHIR</FunctionalReferenceID>
			<ID>24GBAARY9K48AABA00</ID>
			<VersionID>1</VersionID>
		</Declaration>
	</Response>
</MetaData>