<MetaData>
	<WCODataModelVersionCode>3.6</WCODataModelVersionCode>
	<WCOTypeName>RES</WCOTypeName>
	<ResponsibleCountryCode/>
	<ResponsibleAgencyName/>
	<AgencyAssignedCustomizationCode/>
	<AgencyAssignedCustomizationVersionCode/>
	<Response>
		<FunctionCode>13</FunctionCode>
		<FunctionalReferenceID>023fc102984e4f0f902d374b868f228f</FunctionalReferenceID>
		<IssueDateTime>
			<DateTimeString formatCode="304">20251113111008Z</DateTimeString>
		</IssueDateTime>
		<Bank>
			<ReferenceID>BARCGB22</ReferenceID>
			<ID>GB16BARC20051723372545</ID>
		</Bank>
		<Status>
			<NameCode>4</NameCode>
		</Status>
		<Declaration>
			<FunctionalReferenceID>U.78696180BNWL</FunctionalReferenceID>
			<ID>25GBCK6YEQTF0M4A00</ID>
			<VersionID>1</VersionID>
			<GoodsShipment>
				<GovernmentAgencyGoodsItem>
					<SequenceNumeric>1</SequenceNumeric>
					<Commodity/>
				</GovernmentAgencyGoodsItem>
			</GoodsShipment>
		</Declaration>
	</Response>
</MetaData>