<ns2:inventoryLinkingMovementTotalsResponse xmlns="http://gov.uk/customs/inventoryLinking/gatewayHeader/v1"
                                            xmlns:ns2="http://gov.uk/customs/inventoryLinking/v1">
	<ns2:messageCode>ERS</ns2:messageCode>
	<ns2:goodsLocation>GBAULGWLGWLGW</ns2:goodsLocation>
	<ns2:goodsArrivalDateTime>2022-06-08T13:56:00.000Z</ns2:goodsArrivalDateTime>
	<ns2:movementReference>Movement14</ns2:movementReference>
	<ns2:entry>
		<ns2:ucrBlock>
			<ns2:ucr>2GB427168118378-0806A1</ns2:ucr>
			<ns2:ucrType>D</ns2:ucrType>
		</ns2:ucrBlock>
		<ns2:entryStatus>
			<ns2:roe>6</ns2:roe>
			<ns2:soe>3</ns2:soe>
		</ns2:entryStatus>
	</ns2:entry>
</ns2:inventoryLinkingMovementTotalsResponse>