<MetaData>
    <WCODataModelVersionCode>3.6</WCODataModelVersionCode>
    <WCOTypeName>RES</WCOTypeName>
    <ResponsibleCountryCode/>
    <ResponsibleAgencyName/>
    <AgencyAssignedCustomizationCode/>
    <AgencyAssignedCustomizationVersionCode/>
    <Response>
        <FunctionCode>13</FunctionCode>
        <FunctionalReferenceID>88ddde1f660d4cd28c5a172d3f776fc6</FunctionalReferenceID>
        <IssueDateTime>
            <DateTimeString formatCode="304">20220804151329+01</DateTimeString>
        </IssueDateTime>
        <Bank>
            <ReferenceID>CITIGB2LLON</ReferenceID>
            <ID>GB25CITI08320011963155</ID>
        </Bank>
        <Status>
            <NameCode>4</NameCode>
        </Status>
        <Declaration>
            <FunctionalReferenceID>TT_IM107a_v0.1_0408_15</FunctionalReferenceID>
            <ID>22GB8K25PWEQUL0AR1</ID>
            <VersionID>1</VersionID>
            <GoodsShipment>
                <GovernmentAgencyGoodsItem>
                    <SequenceNumeric>1</SequenceNumeric>
                    <Commodity>
                        <DutyTaxFee>
                            <AdValoremTaxBaseAmount currencyID="GBP">2000.00</AdValoremTaxBaseAmount>
                            <DeductAmount currencyID="GBP">0.00</DeductAmount>
                            <DutyRegimeCode>100</DutyRegimeCode>
                            <TaxRateNumeric>11.00</TaxRateNumeric>
                            <TypeCode>A50</TypeCode>
                            <Payment>
                                <TaxAssessedAmount currencyID="GBP">220.00</TaxAssessedAmount>
                                <PaymentAmount currencyID="GBP">220.00</PaymentAmount>
                            </Payment>
                        </DutyTaxFee>
                        <DutyTaxFee>
                            <AdValoremTaxBaseAmount currencyID="GBP">220.00</AdValoremTaxBaseAmount>
                            <DeductAmount currencyID="GBP">0.00</DeductAmount>
                            <DutyRegimeCode>100</DutyRegimeCode>
                            <TaxRateNumeric>0.00</TaxRateNumeric>
                            <TypeCode>B05</TypeCode>
                            <Payment>
                                <TaxAssessedAmount currencyID="GBP">0.00</TaxAssessedAmount>
                                <PaymentAmount currencyID="GBP">0.00</PaymentAmount>
                            </Payment>
                        </DutyTaxFee>
                        <DutyTaxFee>
                            <AdValoremTaxBaseAmount currencyID="GBP">2000.00</AdValoremTaxBaseAmount>
                            <DeductAmount currencyID="GBP">0.00</DeductAmount>
                            <DutyRegimeCode>100</DutyRegimeCode>
                            <TaxRateNumeric>0.00</TaxRateNumeric>
                            <TypeCode>B00</TypeCode>
                            <Payment>
                                <TaxAssessedAmount currencyID="GBP">0.00</TaxAssessedAmount>
                                <PaymentAmount currencyID="GBP">0.00</PaymentAmount>
                            </Payment>
                        </DutyTaxFee>
                    </Commodity>
                </GovernmentAgencyGoodsItem>
            </GoodsShipment>
        </Declaration>
    </Response>
</MetaData>

