<MetaData>
	<WCODataModelVersionCode>3.6</WCODataModelVersionCode>
	<WCOTypeName>RES</WCOTypeName>
	<ResponsibleCountryCode/>
	<ResponsibleAgencyName/>
	<AgencyAssignedCustomizationCode/>
	<AgencyAssignedCustomizationVersionCode/>
	<Response>
		<FunctionCode>02</FunctionCode>
		<FunctionalReferenceID>ac4cc60f6299483b9fce67838625e84b</FunctionalReferenceID>
		<IssueDateTime>
			<DateTimeString formatCode="304">20220309131730Z</DateTimeString>
		</IssueDateTime>
		<Declaration>
			<FunctionalReferenceID>TT_IM77a_v1.1_0903_01</FunctionalReferenceID>
			<ID>22GB2OIZNQAP8JPA05</ID>
			<VersionID>1</VersionID>
		</Declaration>
	</Response>
</MetaData>