<MetaData>
	<WCODataModelVersionCode>3.6</WCODataModelVersionCode>
	<WCOTypeName>RES</WCOTypeName>
	<ResponsibleCountryCode/>
	<ResponsibleAgencyName/>
	<AgencyAssignedCustomizationCode/>
	<AgencyAssignedCustomizationVersionCode/>
	<Response>
		<FunctionCode>09</FunctionCode>
		<FunctionalReferenceID>99dd7109a0c74d66919152dee18238b5</FunctionalReferenceID>
		<IssueDateTime>
			<DateTimeString formatCode="304">20240312104641Z</DateTimeString>
		</IssueDateTime>
		<AdditionalInformation>
			<StatementCode>A2</StatementCode>
			<StatementTypeCode>AFB</StatementTypeCode>
		</AdditionalInformation>
		<Declaration>
			<FunctionalReferenceID>7849431LE06U</FunctionalReferenceID>
			<ID>24GB2U3CTU4ZRPSAR4</ID>
			<VersionID>1</VersionID>
		</Declaration>
	</Response>
</MetaData>