<MetaData>
	<WCODataModelVersionCode>3.6</WCODataModelVersionCode>
	<WCOTypeName>RES</WCOTypeName>
	<ResponsibleCountryCode/>
	<ResponsibleAgencyName/>
	<AgencyAssignedCustomizationCode/>
	<AgencyAssignedCustomizationVersionCode/>
	<Response>
		<FunctionCode>01</FunctionCode>
		<FunctionalReferenceID>fdb98a3f42e8450fb9ba56eec53b4975</FunctionalReferenceID>
		<IssueDateTime>
			<DateTimeString formatCode="304">20241206155231Z</DateTimeString>
		</IssueDateTime>
		<Declaration>
			<AcceptanceDateTime>
				<DateTimeString formatCode="304">20241206155230Z</DateTimeString>
			</AcceptanceDateTime>
			<FunctionalReferenceID>U.7867523NHYHA</FunctionalReferenceID>
			<ID>24GBDIRQ9EO5YKPAA2</ID>
			<VersionID>2</VersionID>
		</Declaration>
	</Response>
</MetaData>