<MetaData>
	<WCODataModelVersionCode>3.6</WCODataModelVersionCode>
	<WCOTypeName>RES</WCOTypeName>
	<ResponsibleCountryCode/>
	<ResponsibleAgencyName/>
	<AgencyAssignedCustomizationCode/>
	<AgencyAssignedCustomizationVersionCode/>
	<Response>
		<FunctionCode>09</FunctionCode>
		<FunctionalReferenceID>40d66d1cc667455783460592a48fdfbb</FunctionalReferenceID>
		<IssueDateTime>
			<DateTimeString formatCode="304">20240903082330Z</DateTimeString>
		</IssueDateTime>
		<AdditionalInformation>
			<StatementCode>A2</StatementCode>
			<StatementTypeCode>AFB</StatementTypeCode>
		</AdditionalInformation>
		<Declaration>
			<FunctionalReferenceID>7849431PKQ9E</FunctionalReferenceID>
			<ID>24GB9S0B0L4S6IHAR2</ID>
			<VersionID>1</VersionID>
		</Declaration>
	</Response>
</MetaData>