<MetaData>
    <WCODataModelVersionCode>3.6</WCODataModelVersionCode>
    <WCOTypeName>RES</WCOTypeName>
    <ResponsibleCountryCode/>
    <ResponsibleAgencyName/>
    <AgencyAssignedCustomizationCode/>
    <AgencyAssignedCustomizationVersionCode/>
    <Response>
        <FunctionCode>09</FunctionCode>
        <FunctionalReferenceID>3fafea9739c94760a7a2dfd2a75f4ff5</FunctionalReferenceID>
        <IssueDateTime>
            <DateTimeString formatCode="304">20240617152122+01</DateTimeString>
        </IssueDateTime>
        <AdditionalInformation>
            <StatementCode>A2</StatementCode>
            <StatementTypeCode>AFB</StatementTypeCode>
        </AdditionalInformation>
        <Declaration>
            <FunctionalReferenceID>784732383ZKJ</FunctionalReferenceID>
            <ID>24GB6OWMQ5JP94GA02</ID>
            <VersionID>2</VersionID>
        </Declaration>
    </Response>
</MetaData>