<MetaData>
    <WCODataModelVersionCode>3.6</WCODataModelVersionCode>
    <WCOTypeName>RES</WCOTypeName>
    <ResponsibleCountryCode/>
    <ResponsibleAgencyName/>
    <AgencyAssignedCustomizationCode/>
    <AgencyAssignedCustomizationVersionCode/>
    <Response>
        <FunctionCode>09</FunctionCode>
        <FunctionalReferenceID>47a0d699e61d4c69b70d1e05ae31011d</FunctionalReferenceID>
        <IssueDateTime>
            <DateTimeString formatCode="304">20221128115755Z</DateTimeString>
        </IssueDateTime>
        <AdditionalInformation>
            <StatementCode>A2</StatementCode>
            <StatementTypeCode>AFB</StatementTypeCode>
        </AdditionalInformation>
        <Declaration>
            <FunctionalReferenceID>NIP_266_TC01_2811_01</FunctionalReferenceID>
            <ID>22GBD5OE5FHL5V3AR9</ID>
            <VersionID>1</VersionID>
        </Declaration>
    </Response>
</MetaData>