<md:MetaData xsi:schemaLocation="urn:wco:datamodel:WCO:DocumentMetaData-DMS:2 ../DocumentMetaData_2_DMS.xsd "
           	xmlns:md="urn:wco:datamodel:WCO:DocumentMetaData-DMS:2"
           	xmlns:ds="urn:wco:datamodel:WCO:MetaData_DS-DMS:2"
           	xmlns:clm63055="urn:un:unece:uncefact:codelist:standard:UNECE:AgencyIdentificationCode:D12B"
           	xmlns:xsi="http://www.w3.org/2001/XMLSchema-instance"
           	xmlns="urn:wco:datamodel:WCO:DEC-DMS:2"
           	>
	<md:WCODataModelVersionCode>3.6</md:WCODataModelVersionCode>
	<md:WCOTypeName>DEC</md:WCOTypeName>
	<md:ResponsibleCountryCode>GB</md:ResponsibleCountryCode>
	<md:ResponsibleAgencyName>HMRC</md:ResponsibleAgencyName>
	<md:AgencyAssignedCustomizationVersionCode>v2.1</md:AgencyAssignedCustomizationVersionCode>
	<Declaration xsi:schemaLocation="urn:wco:datamodel:WCO:DEC-DMS:2 ../WCO_DEC_2_DMS.xsd "
           		xmlns:clm63055="urn:un:unece:uncefact:codelist:standard:UNECE:AgencyIdentificationCode:D12B"
           		xmlns:xsi="http://www.w3.org/2001/XMLSchema-instance"
           		xmlns="urn:wco:datamodel:WCO:DEC-DMS:2"
           		xmlns:udt="urn:un:unece:uncefact:data:standard:UnqualifiedDataType:6"
           		xmlns:p1="urn:wco:datamodel:WCO:Declaration_DS:DMS:2"
           		xmlns:clm5ISO42173A="urn:un:unece:uncefact:codelist:standard:ISO:ISO3AlphaCurrencyCode:2012-08-31"
           		>
		<!-- 
			This amendment is provided with the Electronic Licence status code EE to exhaust the licence. 
			Using the status EE code will exhaust the licence, which will then be refreshed at 3 AM the following day 
			to make it available again for testing.
			For repeat testing on the same day, document code EP can be used instead to avoid exhausting the licence.
		-->
		<!--Function Code of 13 to represent Request (Additional Message)-->
		<FunctionCode>13</FunctionCode>
		<!--The trader assigned reference to the additional message. 
			Note that this reference is independent of the declaration. -->
		<FunctionalReferenceID>R280_TC02AMND_002</FunctionalReferenceID>
		<!--Declaration ID of the corresponding Declaration to be amended-->
		<ID>21GB31AJB9S50C90R6</ID>
		<!--Defines the type of additional message - in this scenario, COR to indicate that this additional message 
			is an amendment. -->
		<TypeCode>COR</TypeCode>
		<AdditionalInformation>
			<!--Textual description of the reason for amendment-->
			<StatementDescription>Amending Status code on licence to EE</StatementDescription>
			<!--The type of Additional Information. 
				'AES' should always be used for Cancellations and Amendments to indicate a free text reason is 
				being provided.-->
			<StatementTypeCode>AES</StatementTypeCode>
			<!--The two pointer elements below point to the Declaration (42A) and the Amendment (06A) in the Declaration 
				(which can be seen below). 
				This is so that the textual description can be linked to its corresponding amendment reason code.-->
			<Pointer>
				<SequenceNumeric>1</SequenceNumeric>
				<DocumentSectionCode>42A</DocumentSectionCode>
			</Pointer>
			<Pointer>
				<SequenceNumeric>1</SequenceNumeric>
				<DocumentSectionCode>06A</DocumentSectionCode>
			</Pointer>
		</AdditionalInformation>
		<!--Details of the amendment to be made to the Declaration-->
		<Amendment>
			<!--Used to indicate the reason for the amendment - in this scenario, a code of 25 to indicate that 
				a License is being amended.-->
			<ChangeReasonCode>25</ChangeReasonCode>
			<!--Pointers describe the declaration tree down to the part of the Declaration which needs to be amended 
				as follows: Declaration (42A) -> GoodsShipment (67A) -> GovernmentAgencyGoodsItem (68A) 
				-> Additional Document (02A) -> Tag 360 for LPCOExemptionCode) -->
			<Pointer>
				<SequenceNumeric>1</SequenceNumeric>
				<DocumentSectionCode>42A</DocumentSectionCode>
			</Pointer>
			<Pointer>
				<SequenceNumeric>1</SequenceNumeric>
				<DocumentSectionCode>67A</DocumentSectionCode>
			</Pointer>
			<Pointer>
				<SequenceNumeric>1</SequenceNumeric>
				<DocumentSectionCode>68A</DocumentSectionCode>
			</Pointer>
			<Pointer>
				<SequenceNumeric>1</SequenceNumeric>
				<DocumentSectionCode>02A</DocumentSectionCode>
				<TagID>360</TagID>
			</Pointer>
		</Amendment>
		<!--The below details the Declaration data that is being amended. As described by the pointer structure above, 
			the information below shows that the Status Code (LPCOExemptionCode) is being amended and the new value 
			of EE is included below.
			N.B: Using the status EE code will exhaust the licence. -->
		<GoodsShipment>
			<GovernmentAgencyGoodsItem>
				<SequenceNumeric>1</SequenceNumeric>
				<AdditionalDocument>
					<CategoryCode>9</CategoryCode>
					<ID>GBOIL1234567G-0001</ID>
					<TypeCode>100</TypeCode>
					<!--Document code of EE indicates Electronic details on CDS – exhausted.
						N.B: Using the status EE code will exhaust the licence, which will then be refreshed at 3 AM 
						the following day to make it available again for testing. 
						For repeat testing on the same day, document code EP can be used instead to avoid exhausting 
						the licence. -->
					<LPCOExemptionCode>EE</LPCOExemptionCode>
					<WriteOff>
						<QuantityQuantity unitCode="KGM#G">4</QuantityQuantity>
					</WriteOff>
				</AdditionalDocument>
			</GovernmentAgencyGoodsItem>
		</GoodsShipment>
	</Declaration>
</md:MetaData>